alveoleye/__init__.py
alveoleye/_action_box.py
alveoleye/_boxes.py
alveoleye/_export_operations.py
alveoleye/_gui_creator.py
alveoleye/_layers_editor.py
alveoleye/_reader.py
alveoleye/_rules.py
alveoleye/_sample_data.py
alveoleye/_widget.py
alveoleye/_workers.py
alveoleye/_writer.py
alveoleye/config.json
alveoleye/dark_theme.css
alveoleye/light_theme.css
alveoleye/napari.yaml
alveoleye/_tests/__init__.py
alveoleye/_tests/test_assessments.py
alveoleye/_tests/test_lungcv.py
alveoleye/_tests/test_plugin.py
alveoleye/_tests/test_postprocessing.py
alveoleye/_tests/test_reader.py
alveoleye/data/__init__.py
alveoleye/lungcv/__init__.py
alveoleye/lungcv/assessments.py
alveoleye/lungcv/model_operations.py
alveoleye/lungcv/postprocessor.py
alveoleye/lungcv/mrcnn/__init__.py
alveoleye/lungcv/mrcnn/coco_eval.py
alveoleye/lungcv/mrcnn/coco_utils.py
alveoleye/lungcv/mrcnn/engine.py
alveoleye/lungcv/mrcnn/group_by_aspect_ratio.py
alveoleye/lungcv/mrcnn/train.py
alveoleye/lungcv/mrcnn/transforms.py
alveoleye/lungcv/mrcnn/utils.py
AlveolEye-0.1.4.dist-info/LICENSE
AlveolEye-0.1.4.dist-info/METADATA
AlveolEye-0.1.4.dist-info/WHEEL
AlveolEye-0.1.4.dist-info/entry_points.txt
AlveolEye-0.1.4.dist-info/top_level.txt
AlveolEye-0.1.4.dist-info/RECORD
